{
  "openapi": "3.0.1",
  "info": {
    "title": "EcommerceWebApi",
    "version": "1.0"
  },
  "paths": {
    "/api/Cart": {
      "get": {
        "tags": [
          "Cart"
        ],
        "responses": {
          "200": {
            "description": "OK"
          }
        }
      },
      "post": {
        "tags": [
          "Cart"
        ],
        "requestBody": {
          "content": {
            "application/json": {
              "schema": {
                "$ref": "#/components/schemas/Cart"
              }
            },
            "text/json": {
              "schema": {
                "$ref": "#/components/schemas/Cart"
              }
            },
            "application/*+json": {
              "schema": {
                "$ref": "#/components/schemas/Cart"
              }
            }
          }
        },
        "responses": {
          "200": {
            "description": "OK"
          }
        }
      }
    },
    "/api/Cart/{id}": {
      "get": {
        "tags": [
          "Cart"
        ],
        "parameters": [
          {
            "name": "id",
            "in": "path",
            "required": true,
            "schema": {
              "type": "integer",
              "format": "int32"
            }
          }
        ],
        "responses": {
          "200": {
            "description": "OK"
          }
        }
      },
      "put": {
        "tags": [
          "Cart"
        ],
        "parameters": [
          {
            "name": "id",
            "in": "path",
            "required": true,
            "schema": {
              "type": "integer",
              "format": "int32"
            }
          }
        ],
        "requestBody": {
          "content": {
            "application/json": {
              "schema": {
                "$ref": "#/components/schemas/Cart"
              }
            },
            "text/json": {
              "schema": {
                "$ref": "#/components/schemas/Cart"
              }
            },
            "application/*+json": {
              "schema": {
                "$ref": "#/components/schemas/Cart"
              }
            }
          }
        },
        "responses": {
          "200": {
            "description": "OK"
          }
        }
      },
      "delete": {
        "tags": [
          "Cart"
        ],
        "parameters": [
          {
            "name": "id",
            "in": "path",
            "required": true,
            "schema": {
              "type": "integer",
              "format": "int32"
            }
          }
        ],
        "responses": {
          "200": {
            "description": "OK"
          }
        }
      }
    },
    "/api/Orders": {
      "get": {
        "tags": [
          "Orders"
        ],
        "responses": {
          "200": {
            "description": "OK",
            "content": {
              "text/plain": {
                "schema": {
                  "type": "array",
                  "items": {
                    "$ref": "#/components/schemas/Order"
                  }
                }
              },
              "application/json": {
                "schema": {
                  "type": "array",
                  "items": {
                    "$ref": "#/components/schemas/Order"
                  }
                }
              },
              "text/json": {
                "schema": {
                  "type": "array",
                  "items": {
                    "$ref": "#/components/schemas/Order"
                  }
                }
              }
            }
          }
        }
      },
      "post": {
        "tags": [
          "Orders"
        ],
        "requestBody": {
          "content": {
            "application/json": {
              "schema": {
                "$ref": "#/components/schemas/Order"
              }
            },
            "text/json": {
              "schema": {
                "$ref": "#/components/schemas/Order"
              }
            },
            "application/*+json": {
              "schema": {
                "$ref": "#/components/schemas/Order"
              }
            }
          }
        },
        "responses": {
          "200": {
            "description": "OK"
          }
        }
      }
    },
    "/api/Orders/{id}": {
      "get": {
        "tags": [
          "Orders"
        ],
        "parameters": [
          {
            "name": "id",
            "in": "path",
            "required": true,
            "schema": {
              "type": "integer",
              "format": "int32"
            }
          }
        ],
        "responses": {
          "200": {
            "description": "OK",
            "content": {
              "text/plain": {
                "schema": {
                  "$ref": "#/components/schemas/Order"
                }
              },
              "application/json": {
                "schema": {
                  "$ref": "#/components/schemas/Order"
                }
              },
              "text/json": {
                "schema": {
                  "$ref": "#/components/schemas/Order"
                }
              }
            }
          }
        }
      },
      "delete": {
        "tags": [
          "Orders"
        ],
        "parameters": [
          {
            "name": "id",
            "in": "path",
            "required": true,
            "schema": {
              "type": "integer",
              "format": "int32"
            }
          }
        ],
        "responses": {
          "200": {
            "description": "OK"
          }
        }
      }
    },
    "/api/Orders/{id}/status": {
      "put": {
        "tags": [
          "Orders"
        ],
        "parameters": [
          {
            "name": "id",
            "in": "path",
            "required": true,
            "schema": {
              "type": "integer",
              "format": "int32"
            }
          }
        ],
        "requestBody": {
          "content": {
            "application/json": {
              "schema": {
                "type": "string"
              }
            },
            "text/json": {
              "schema": {
                "type": "string"
              }
            },
            "application/*+json": {
              "schema": {
                "type": "string"
              }
            }
          }
        },
        "responses": {
          "200": {
            "description": "OK"
          }
        }
      }
    },
    "/api/Orders/{id}/payment": {
      "put": {
        "tags": [
          "Orders"
        ],
        "parameters": [
          {
            "name": "id",
            "in": "path",
            "required": true,
            "schema": {
              "type": "integer",
              "format": "int32"
            }
          }
        ],
        "requestBody": {
          "content": {
            "application/json": {
              "schema": {
                "type": "string"
              }
            },
            "text/json": {
              "schema": {
                "type": "string"
              }
            },
            "application/*+json": {
              "schema": {
                "type": "string"
              }
            }
          }
        },
        "responses": {
          "200": {
            "description": "OK"
          }
        }
      }
    },
    "/api/Orders/user/{userId}": {
      "get": {
        "tags": [
          "Orders"
        ],
        "parameters": [
          {
            "name": "userId",
            "in": "path",
            "required": true,
            "schema": {
              "type": "integer",
              "format": "int32"
            }
          }
        ],
        "responses": {
          "200": {
            "description": "OK",
            "content": {
              "text/plain": {
                "schema": {
                  "type": "array",
                  "items": {
                    "$ref": "#/components/schemas/Order"
                  }
                }
              },
              "application/json": {
                "schema": {
                  "type": "array",
                  "items": {
                    "$ref": "#/components/schemas/Order"
                  }
                }
              },
              "text/json": {
                "schema": {
                  "type": "array",
                  "items": {
                    "$ref": "#/components/schemas/Order"
                  }
                }
              }
            }
          }
        }
      }
    }
  },
  "components": {
    "schemas": {
      "Cart": {
        "required": [
          "quantity",
          "totalPrice"
        ],
        "type": "object",
        "properties": {
          "cartItemID": {
            "type": "integer",
            "format": "int32"
          },
          "productID": {
            "type": "integer",
            "format": "int32"
          },
          "quantity": {
            "type": "integer",
            "format": "int32"
          },
          "totalPrice": {
            "type": "number",
            "format": "double"
          }
        },
        "additionalProperties": false
      },
      "Order": {
        "required": [
          "shippingAddress",
          "totalPrice",
          "userID"
        ],
        "type": "object",
        "properties": {
          "orderID": {
            "type": "integer",
            "format": "int32"
          },
          "userID": {
            "type": "integer",
            "format": "int32"
          },
          "totalPrice": {
            "minimum": 0.01,
            "type": "number",
            "format": "double"
          },
          "shippingAddress": {
            "maxLength": 500,
            "minLength": 0,
            "type": "string"
          },
          "orderStatus": {
            "type": "string",
            "nullable": true
          },
          "paymentStatus": {
            "type": "string",
            "nullable": true
          }
        },
        "additionalProperties": false
      }
    }
  }
}